movies_download/__init__.py
movies_download/main.py
movies_download-0.0.2.dist-info/LICENSE
movies_download-0.0.2.dist-info/METADATA
movies_download-0.0.2.dist-info/WHEEL
movies_download-0.0.2.dist-info/top_level.txt
movies_download-0.0.2.dist-info/RECORD
