Metadata-Version: 2.1
Name: movies-download
Version: 0.0.2
Summary: 视频下载助手
Home-page: https://gitee.com/cgq/movies-download
Author: 碧海苍鹰
Author-email: 碧海苍鹰 <348249063@qq.com>
License: MIT
Project-URL: Homepage, https://gitee.com/cgq/movies-download
Project-URL: Bug Tracker, https://gitee.com/cgq/movies-download/issues
Classifier: Programming Language :: Python :: 3
Classifier: License :: OSI Approved :: MIT License
Classifier: Operating System :: OS Independent
Requires-Python: >=3.8
License-File: LICENSE
